mr/__init__.py
mr/istarmap.py
mr/meeseeks.py
mr/moment.py
mr/scheduler.py
mr/utils.py
mrmeeseeks-0.5.dist-info/METADATA
mrmeeseeks-0.5.dist-info/WHEEL
mrmeeseeks-0.5.dist-info/licenses/LICENSE
mrmeeseeks-0.5.dist-info/RECORD
