Metadata-Version: 2.1
Name: mrmeeseeks
Version: 0.5
Summary: A Meeseeks that batch processes what you asked for.
Project-URL: Homepage, https://gitlab.com/KirmTwinty/mrmeeseeks
Project-URL: Bug Tracker, https://gitlab.com/KirmTwinty/mrmeeseeks/issues
Author-email: KirmTwinty <thibaud.toullier@inria.fr>
License:                     GNU GENERAL PUBLIC LICENSE
License-File: LICENSE
Classifier: License :: OSI Approved :: GNU General Public License v3 (GPLv3)
Classifier: Operating System :: OS Independent
Classifier: Programming Language :: Python :: 2
Classifier: Programming Language :: Python :: 3
Requires-Python: >=2.5
Requires-Dist: pyyaml
Requires-Dist: rich
